MANIFEST.in
README.md
RELEASE-VERSION
setup.py
version.py
genomicsqlite/__init__.py
genomicsqlite/__main__.py
genomicsqlite/libgenomicsqlite.dylib
genomicsqlite/libgenomicsqlite.so
genomicsqlite/sqlite_web_dbi.py
genomicsqlite.egg-info/PKG-INFO
genomicsqlite.egg-info/SOURCES.txt
genomicsqlite.egg-info/dependency_links.txt
genomicsqlite.egg-info/entry_points.txt
genomicsqlite.egg-info/top_level.txt