Metadata-Version: 2.1
Name: genomicsqlite
Version: 0.9.2
Summary: Genomics Extension for SQLite
Home-page: https://github.com/mlin/GenomicSQLite
Author: Mike Lin
Author-email: dna@mlin.net
License: Apache
Platform: UNKNOWN
Requires-Python: >=3.6
